mizuna/__init__.py
mizuna/_version.py
mizuna/git.py
mizuna/mizuna.py
mizuna/utils/__init__.py
mizuna/utils/utils.py
tests/__init__.py
tests/test_mizuna.py
mizuna-0.2.4.dist-info/LICENSE
mizuna-0.2.4.dist-info/METADATA
mizuna-0.2.4.dist-info/WHEEL
mizuna-0.2.4.dist-info/top_level.txt
mizuna-0.2.4.dist-info/RECORD
