Metadata-Version: 2.1
Name: mizuna
Version: 0.2.4
Summary: Mizuna is a package that automates uploading visualizations to Overleaf projects (or git repositories).
Home-page: https://github.com/srodriguez1850/Mizuna
Author: Sebastian Rodriguez
Author-email: s.rodriguez1850@outlook.com
License: MIT License
Project-URL: Bug Reports, https://github.com/srodriguez1850/Mizuna/issues
Project-URL: Source, https://github.com/srodriguez1850/Mizuna/issues
Keywords: python,workflow,data-science,latex,overleaf,jupyter,matplotlib,seaborn,ggplot,plotly
Platform: UNKNOWN
Classifier: Development Status :: 2 - Pre-Alpha
Classifier: Intended Audience :: Developers
Classifier: Intended Audience :: Science/Research
Classifier: Programming Language :: Python :: 3
Classifier: Operating System :: MacOS :: MacOS X
Classifier: Operating System :: Microsoft :: Windows
Classifier: License :: OSI Approved :: MIT License
Classifier: Topic :: Utilities
Requires-Python: >=3.6, <4
